r4c/__init__.py
r4c/actor.py
r4c/envy.py
r4c/helpers.py
r4c/policy_gradients/__init__.py
r4c/policy_gradients/pg_actor.py
r4c/policy_gradients/pg_actor_module.py
r4c/policy_gradients/a2c/__init__.py
r4c/policy_gradients/a2c/a2c_actor.py
r4c/policy_gradients/a2c/a2c_actor_module.py
r4c/policy_gradients/actor_critic/__init__.py
r4c/policy_gradients/actor_critic/ac_actor.py
r4c/policy_gradients/actor_critic/ac_critic.py
r4c/policy_gradients/actor_critic/ac_critic_module.py
r4c/qlearning/__init__.py
r4c/qlearning/ql_actor.py
r4c/qlearning/dqn/__init__.py
r4c/qlearning/dqn/dqn_actor.py
r4c/qlearning/dqn/dqn_actor_module.py
r4c/qlearning/qtable/__init__.py
r4c/qlearning/qtable/qt_actor.py
r4c-0.2.0.dist-info/METADATA
r4c-0.2.0.dist-info/WHEEL
r4c-0.2.0.dist-info/top_level.txt
r4c-0.2.0.dist-info/RECORD
