Metadata-Version: 2.1
Name: r4c
Version: 0.2.0
Summary: Reinforcement with PyTorch
Home-page: https://github.com/piteren/hpmser.git
Author: Piotr Niewinski
Author-email: pioniewinski@gmail.com
License: MIT
Requires-Dist: numpy
Requires-Dist: pypaq
Requires-Dist: torchness
